{
  "apply": "Terapkan",
  "loading_label": "Memuat",
  "participants_header": "Peserta",
  "aria_start_transcript_only": "Mulai transkripsi saja",
  "aria_start_call_transcription": "Mulai transkripsi",
  "aria_stop_call_transcription": "Hentikan transkripsi",
  "calling_admit_all_dialog_button": "Izinkan masuk semua orang",
  "calling_confirm_admit_all_dialog_title": "Izinkan masuk semua orang di lobi?",
  "calling_confirm_admit_all_dialog_text": "Beberapa orang yang sedang menunggu tidak ditampilkan.",
  "calling_loading_participants_in_lobby": "Memuat peserta di lobi",
  "calling_error_loading_participants_in_lobby": "Gagal memuat peserta di lobi, coba lagi.",
  "calling_see_full_list_dialog_button": "Lihat siapa yang menunggu",
  "breakoutroom_return_to_main": "Kembali",
  "breakoutroom_return_to_main_tooltip": "Kembali ke rapat utama",
  "calling_app_loading": "Memuat...",
  "calling_audience_background_settings_dialog_header_description": "Mode bersama – pilih pemandangan baru",
  "calling_audience_background_settings_dialog_description": "Semua adegan.",
  "calling_audience_background_settings_header": "Pilih pemandangan",
  "calling_audience_background_disclaimer_tooltip": "Pemandangan ini akan berubah untuk semua orang",
  "calling_e2ee_status_title": "Enkripsi ujung-ke-ujung diaktifkan untuk panggilan ini",
  "calling_e2ee_status_fail_title": "Tidak dienkripsi ujung ke ujung",
  "calling_e2ee_status_description": "Verifikasi enkripsi panggilan Anda dengan memastikan nomor di bawah ini sama untuk Anda berdua. ",
  "calling_e2ee_status_default_call_description": "Panggilan ini diamankan oleh enkripsi data Teams.",
  "calling_e2ee_status_default_meeting_description": "Rapat ini diamankan dengan enkripsi data Microsoft Teams.",
  "calling_e2ee_status_icon_label": "Status enkripsi",
  "calling_e2ee_status_learn_more": "Pelajari selengkapnya",
  "calling_e2ee_status_label": "Angka enkripsi ujung ke ujung",
  "e2ee_call_chat_info_banner": "Obrolan diamankan dengan enkripsi data Teams. Hanya panggilan yang dapat dienkripsi ujung ke ujung saat ini.",
  "calling_park_success_status": "Panggilan dijeda",
  "calling_park_copy_pickup_code": "Salin kode",
  "calling_park_pickup_code": "Bagikan kode {{pickupCode}} ini untuk menerima panggilan",
  "calling_change_audience_scene": "Ubah pemandangan",
  "calling_change_audience_scene_coachmark": "Pilih Edit untuk memilih pemandangan lain kapan saja.",
  "calling_consulting_chat_mode": "Obrolan",
  "calling_consulting_teams_audio_call_mode": "Panggilan audio Teams",
  "calling_consulting_transfer": "Transfer {{endUser}} ke {{consultee}}",
  "calling_pre_join_webinar_privacy_message": "Anda bergabung dengan akun kerja atau sekolah. Jika ingin bergabung secara anonim atau dengan akun lain, <0></0>",
  "calling_pre_join_webinar_privacy_message_see_here": "lihat di sini.",
  "calling_tab_details_title": "Detail",
  "calling_tab_quick_reply_placeholder": "Kirim pesan cepat",
  "calling_tab_recording_and_transcript_title": "Perekaman dan transkripsi",
  "calling_tab_transcript_title": "Transkrip",
  "calling_tab_transcript_back": "Kembali",
  "calling_transfer_failed_message": "Transfer gagal",
  "calling_toggle_whiteboard_video_effect": "Aktifkan/nonaktifkan berbagi papan tulis (pratinjau)",
  "calling_start_liveCaptions": "Aktifkan keterangan langsung",
  "calling_stop_liveCaptions": "Nonaktifkan keterangan langsung",
  "calling_captions_settings": "Pengaturan keterangan",
  "calling_captions_change_spoken_language": "Change spoken language",
  "calling_captions_track": "Trek: {{currentTrack}}",
  "calling_captions_language_ar_ae": "Arab (Uni Emirat Arab)",
  "calling_captions_language_ar_sa": "Arab (Arab Saudi)",
  "calling_captions_language_da_dk": "Dansk (Denmark)",
  "calling_captions_language_de_de": "Jerman (Jerman)",
  "calling_captions_language_en_au": "Inggris (Australia)",
  "calling_captions_language_en_ca": "Inggris (Kanada)",
  "calling_captions_language_en_gb": "Inggris (UK)",
  "calling_captions_language_en_in": "Inggris (India)",
  "calling_captions_language_en_nz": "Inggris (Selandia Baru)",
  "calling_captions_language_en_us": "Inggris (AS)",
  "calling_captions_language_es_es": "Spanyol (Spanyol)",
  "calling_captions_language_es_mx": "Spanyol (Meksiko)",
  "calling_captions_language_fi_fi": "Suomi (Finlandia)",
  "calling_captions_language_fr_ca": "Prancis (Kanada)",
  "calling_captions_language_fr_fr": "Prancis (Prancis)",
  "calling_captions_language_hi_in": "Bahasa Hindi (India)",
  "calling_captions_language_it_it": "Italia (Italia)",
  "calling_captions_language_ja_jp": "Bahasa Jepang (Jepang)",
  "calling_captions_language_ko_kr": "Korea (Korea)",
  "calling_captions_language_nb_no": "Bahasa Norwegia (Norwegia)",
  "calling_captions_language_nl_be": "Belanda (Belgia)",
  "calling_captions_language_nl_nl": "Belanda (Belanda)",
  "calling_captions_language_pl_pl": "Polski (Polandia)",
  "calling_captions_language_pt_br": "Portugis (Brasil)",
  "calling_captions_language_ru_ru": "Rusia (Rusia)",
  "calling_captions_language_sv_se": "Swedia (Swedia)",
  "calling_captions_language_zh_hk": "Mandarin (Kanton, Tradisional)",
  "calling_captions_language_zh_cn": "Mandarin (Mandarin, Sederhana)",
  "calling_captions_language_unknown": "Tidak diketahui",
  "calling_captions_track_ai": "{{currentSpokenLanguage}}",
  "calling_captions_track_cart": "KERANJANG - {{currentSpokenLanguage}}",
  "calling_captions_change_spoken_language_dialog_header": "Set the spoken language for live captions and transcript",
  "calling_captions_available_languages_dropdown_label": "Spoken language",
  "calling_captions_spoken_language_dropdown_title": "Spoken Language",
  "calling_captions_change_language_dialog_subheading": "The language will be set for the meeting group.",
  "calling_captions_change_language_dialog_confirm": "Confirm",
  "calling_captions_change_language_dialog_cancel": "Batal",
  "calling_start_meetingCoach": "Aktifkan Pelatih Rapat",
  "calling_stop_meetingCoach": "Nonaktifkan Pelatih Rapat",
  "calling_start_ndiBroadcast": "Siarkan melalui NDI",
  "calling_stop_ndiBroadcast": "Hentikan siaran NDI",
  "calling_incoming_video_turned_off": "Video masuk dinonaktifkan",
  "calling_incoming_video_turned_on": "Video masuk diaktifkan",
  "calling_toggle_chat_bubbles_on": "Tampilkan gelembung obrolan",
  "calling_anon_prejoin_screen_footer_web": "Untuk pengalaman yang lebih baik, <0></0> atau <1></1>.",
  "calling_anon_prejoin_screen_footer_sign_in": "masuk",
  "calling_anon_prejoin_screen_footer_web_download_app": "unduh aplikasi desktop",
  "calling_anon_prejoin_screen_footer_desktop": "Untuk pengalaman yang lebih baik, <0></0>.",
  "calling_toggle_chat_bubbles_off": "Sembunyikan gelembung",
  "calling_prejoin_header_display_name_input_label": "Ketikkan nama Anda dan bergabung sebagai tamu, atau masuk jika Anda memiliki akun.",
  "calling_prejoin_header_display_name_input_placeholder": "Ketik nama Anda",
  "calling_prejoin_header_display_name_input_tooltip": "Ketik nama Anda di sini sehingga orang lain akan mengetahui Anda saat bergabung.",
  "calling_roster_report_misrecognized_paticipant_popup_item": "Salah dikenali",
  "calling_open_dialpad": "Papan angka",
  "open_meeting_notes": "Catatan rapat",
  "calling_spoken_language_selected_for_transcription": "{{language}} is selected",
  "calling_recording_transcript_started_by": "{{name}} memulai perekaman dan transkripsi",
  "calling_roster_event_group_list_title": "Grup aktivitas",
  "calling_roster_guest_presenters_list_title": "Penyaji eksternal",
  "start_transcript_only_dialog_confirm": "Ya, transkripsikan saja",
  "start_transcript_only_dialog_text": "Rapat ini sudah direkam dan ditranskripsi. Memilih opsi ini akan menghentikan perekaman.",
  "rtflyout_start_recording_only_dialog_confirm": "Ya, rekam saja",
  "rtflyout_start_transcript_only_dialog_text": "Anda sudah mulai merekam dan mentranskripsi rapat ini. Perekaman akan terhenti jika Anda memilih opsi ini.​",
  "rtflyout_stop_recording_and_start_transcript_only_dialog_text": "Anda sudah mulai merekam rapat ini. Perekaman akan terhenti jika Anda memilih opsi ini.​",
  "rtflyout_start_recording_only_dialog_text": "Anda sudah mulai merekam dan mentranskripsi rapat ini. Transkripsi akan terhenti jika Anda memilih opsi ini.​",
  "rtflyout_stop_transcript_and_start_recording_only_dialog_text": "Anda sudah mulai mentranskripsi rapat ini. Transkripsi akan terhenti jika Anda memilih opsi ini.​",
  "rtflyout_start_transcript_only_dialog_title": "Mulai transkripsi saja?",
  "rtflyout_start_recording_only_dialog_title": "Mulai perekaman saja?",
  "start_transcript_only_dialog_title": "Hanya memulai transkripsi?",
  "show_debug_tools": "Tampilkan alat debug",
  "dial_out": "Panggilan keluar",
  "device_settings": "Pengaturan perangkat",
  "meeting_details": "Detail rapat",
  "meeting_details_fluid_copy_link": "Salin tautan",
  "aria_meeting_details_show": "Tampilkan detail rapat",
  "meeting_help": "Bantuan",
  "aria_meeting_notes_show": "Tampilkan catatan rapat",
  "calling_apply_background_effects": "Terapkan efek latar",
  "calling_persistent_background_notification": "Efek latar belakang yang Anda pilih akan muncul di semua panggilan dan rapat.",
  "calling_persistent_background_notification_title": "Latar belakang persisten",
  "breakout_rooms_title": "Ruang terpisah",
  "calling_breakout_rooms_all_users_assigned": "Semua peserta telah ditetapkan",
  "calling_breakout_rooms_unassigned_users_count": "Peserta yang harus ditetapkan ({{unassignedUsersCount}})",
  "calling_breakout_rooms_add_done_aria": "Ruang ditambahkan",
  "calling_breakout_rooms_add_in_progress_aria": "Ruang sedang ditambahkan",
  "calling_breakout_rooms_add_failed_aria": "Ruang gagal ditambahkan",
  "calling_breakout_rooms_assign_participants_failed_aria": "Gagal menetapkan peserta ke ruang",
  "calling_breakout_rooms_assign_participants_in_progress_aria": "Menetapkan peserta ke ruang",
  "calling_breakout_rooms_open_menu_option": "Buka ruang",
  "calling_breakout_rooms_close_menu_option": "Tutup ruang",
  "calling_breakout_rooms_join_menu_option": "Gabung ke ruangan",
  "calling_breakout_rooms_join_in_progress_aria": "Anda sedang bergabung dengan ruang",
  "calling_breakout_rooms_join_failed_aria": "Gagal bergabung dengan ruang",
  "calling_breakout_rooms_close_all_button_content": "Tutup",
  "calling_breakout_rooms_close_all_button_tooltip": "Tutup ruang",
  "calling_breakout_rooms_close_done_aria": "Ruang ditutup",
  "calling_breakout_rooms_close_in_progress_aria": "Ruang sedang ditutup",
  "calling_breakout_rooms_close_failed_aria": "Ruang gagal ditutup",
  "calling_breakout_rooms_start_all_button_content": "Mulai",
  "calling_breakout_rooms_start_all_button_tooltip": "Mulai ruang",
  "calling_breakout_rooms_open_all_button_content": "Buka",
  "calling_breakout_rooms_open_all_button_tooltip": "Buka ruang",
  "calling_breakout_rooms_start_done_aria": "Ruang dimulai",
  "calling_breakout_rooms_start_in_progress_aria": "Ruang sedang dimulai",
  "calling_breakout_rooms_start_failed_aria": "Ruang gagal dimulai",
  "calling_breakout_room_delete_room_done_aria": "Ruang dihapus",
  "calling_breakout_room_delete_room_in_progress_aria": "Ruang sedang dihapus",
  "calling_breakout_room_delete_room_failed_aria": "Ruang gagal dihapus",
  "calling_breakout_room_remove_rooms_dialog_error": "Tidak dapat menghapus ruang.",
  "calling_breakout_room_remove_rooms_done_aria": "Ruang telah dihapus",
  "calling_breakout_room_remove_rooms_in_progress_aria": "Ruang sedang dihapus",
  "calling_breakout_room_rename_room_dialog_header": "Ganti nama \"{{roomName}}\"",
  "calling_breakout_room_rename_room_dialog_confirm_button": "Ubah nama ruang",
  "calling_breakout_room_rename_room_done_aria": "Ruang diganti nama",
  "calling_breakout_room_rename_room_in_progress_aria": "Ruang sedang diganti nama",
  "calling_breakout_room_rename_room_failed_aria": "Ruang gagal diganti nama",
  "calling_breakout_room_opened_state": "Buka",
  "calling_breakout_room_open_room_done_aria": "Ruang dibuka",
  "calling_breakout_room_open_room_in_progress_aria": "Ruang sedang dibuka",
  "calling_breakout_room_open_room_failed_aria": "Ruang gagal dibuka",
  "calling_breakout_room_closed_state": "Tutup",
  "calling_breakout_room_close_room_done_aria": "Ruang ditutup",
  "calling_breakout_room_close_room_in_progress_aria": "Ruang sedang ditutup",
  "calling_breakout_room_close_room_failed_aria": "Ruang gagal ditutup",
  "calling_breakout_room_empty_room_message": "Ruang ini kosong",
  "calling_breakout_room_all_participants_assigned_message": "Semua peserta ditetapkan",
  "calling_breakout_rooms_manage_title": "Kelola ruang",
  "calling_breakout_rooms_calling_state_calling": "Memanggil...",
  "calling_breakout_rooms_ask_to_join": "Minta untuk bergabung",
  "calling_breakout_rooms_calling_state_in_meeting": "Dalam rapat",
  "calling_breakout_rooms_calling_state_failed_to_join": "Gagal bergabung",
  "calling_breakout_rooms_calling_state_moving": "Memindahkan...",
  "calling_breakout_rooms_assign_participants_title": "Tetapkan peserta",
  "calling_breakout_room_assign_button_in_progress": "Menugaskan",
  "calling_breakout_room_action_opening": "Membuka...",
  "calling_breakout_room_action_closing": "Menutup...",
  "calling_breakout_room_action_deleting": "Menghapus...",
  "calling_breakout_room_action_open_failed": "Gagal dibuka",
  "calling_breakout_room_action_close_failed": "Gagal ditutup",
  "calling_breakout_room_action_delete_failed": "Gagal menghapus",
  "calling_breakout_room_assignment_confirmation_dialog_error_content": "Terjadi kesalahan. Coba lagi.",
  "calling_breakout_rooms_save_button_room_edit": "Simpan",
  "calling_breakout_rooms_edit_room": "Edit ruang",
  "dtmf_dialpad_header": "Keypad",
  "dtmf_dialpad_placeholder": "Nomor",
  "dtmf_dialpad_close": "Tutup Tombol Panggil",
  "dtmf_dialpad_input": "Input tombol angka",
  "dialpad_collapsed": "Tombol angka diciutkan",
  "dialpad_expanded": "Tombol angka diperluas",
  "calling_roster_button_request_to_join": "Minta bergabung",
  "calling_roster_button_cancel_request_to_join": "Batal",
  "calling_roster_in_screenshare_from_chat_list_title": "Saat ini di berbagi layar ini",
  "calling_roster_section_title_format": "{{title}} ({{participantsCount}})",
  "calling_roster_see_more": "Lihat selengkapnya",
  "calling_roster_n_more": "+{{participantsCount}} lainnya",
  "calling_error_ufd_region": "Peringatan kesalahan",
  "calling_warning_ufd_region": "Pemberitahuan peringatan",
  "yammer_conversation_link_title": "Buka percakapan Yammer di browser",
  "calling_hide_camera_effects": "Sembunyikan efek video",
  "calling_device_has_been_selected": "dipilih",
  "calling_dial_in_toll_number_aria_label": "Panggilan masuk menggunakan nomor berbayar {{phoneNumber}}, ID konferensi {{conferenceId}}",
  "calling_dial_in_toll_free_number_aria_label": "Panggilan masuk menggunakan nomor bebas pulsa {{phoneNumber}}, ID konferensi {{conferenceId}}",
  "calling_elapsed_meeting_time_aria_label": "{{meetingTitle}}, waktu berlalu {{elapsedTime}}",
  "calling_indictors_accessibility_region": "Indikator panggilan",
  "call_health_panel_root_header": "Kondisi panggilan",
  "call_health_panel_back_to_root": "Kembali untuk memanggil panel root kondisi",
  "call_health_panel_audio_header": "Audio",
  "call_health_panel_video_header": "Video",
  "call_health_panel_screensharing_header": "Berbagi Layar",
  "toggle_call_health_on": "Kondisi panggilan",
  "toggle_call_health_off": "Sembunyikan kondisi panggilan",
  "call_health_panel_learn_more_link_text": "Pelajari selengkapnya",
  "call_health_panel_learn_more_link_aria_label": "Pelajari apa nilai yang umum untuk parameter dalam panel kesehatan panggilan",
  "calling_health_panel_helper_text": "Panggilan Anda sedang menerima data. Sebagian besar metrik di-refresh setiap 15 detik.",
  "calling_health_panel_last_updated_time": "Terakhir diperbarui pukul: {{time}}",
  "calling_health_indicator_receiving": "Rapat Anda dalam kondisi baik dan sedang menerima data",
  "calling_health_view_more_link": "Tampilkan data {{category}} lainnya",
  "calling_health_metrics_list": "Daftar item metrik kesehatan panggilan",
  "calling_health_metric_value": "{{title}}: {{value}}",
  "calling_health_no_data": "--",
  "calling_prejoin_show_background_effects": "Filter latar belakang",
  "calling_prejoin_hide_background_effects": "Filter latar belakang",
  "calling_prejoin_camera_effects_tooltip_not_supported": "Efek kamera tidak didukung di perangkat Anda.",
  "calling_prejoin_camera_effects_tooltip_start_video": "Aktifkan video untuk menggunakan efek kamera",
  "calling_prejoin_show_camera_effects": "Tampilkan opsi efek kamera",
  "calling_prejoin_hide_camera_effects": "Sembunyikan opsi efek kamera",
  "calling_prejoin_show_video_effects_quick_picker": "Tampilkan opsi efek video",
  "calling_prejoin_hide_video_effects_quick_picker": "Sembunyikan opsi efek video",
  "calling_prejoin_hide_video_effects_side_panel": "Sembunyikan panel efek video",
  "calling_prejoin_add_room_list_item_aria_label_prefix": "Item daftar ruang di sekitar dan disarankan. Bergabung dan tambahkan ruang {{roomDisplayName}}",
  "calling_prejoin_room_audio_default_description": "Memerlukan sistem ruang Teams.",
  "calling_prejoin_room_audio_room_selected_subtitle": "Kami akan menambahkan sistem audio ruangan ke rapat setelah Anda bergabung.",
  "calling_prejoin_room_audio_ble_not_supported_subtitle": "Penemuan ruang otomatis belum tersedia di perangkat Anda.",
  "calling_prejoin_room_audio_enable_bluetooth_subtitle": "Aktifkan Bluetooth untuk mendeteksi ruang sekitar secara otomatis.",
  "calling_prejoin_room_audio_add_room": "{{room}} dipilih",
  "calling_prejoin_selected_device_microphone": "Mikrofon {{selectedMicrophone}} dipilih",
  "calling_prejoin_selected_device_speaker": "Speaker {{selectedSpeaker}} dipilih",
  "calling_prejoin_main_landmark_label": "Pengaturan audio dan video",
  "calling_prejoin_header_label": "Pilih pengaturan audio dan video untuk rapat ini",
  "calling_prejoin_join_options_landmark_label": "Opsi bergabung",
  "calling_prejoin_video_preview_landmark_label": "Opsi video",
  "calling_prejoin_audio_options_landmark_label": "Opsi audio",
  "calling_prejoin_choose_audio_and_video": "Pilih opsi video dan audio Anda",
  "calling_prejoin_view_only_notice": "Rapat telah mencapai kapasitas. Anda sedang bergabung dalam mode tampilan-saja.",
  "calling_prejoin_join_via_computer_audio_subtitle": "Gunakan mikrofon dan speaker default.",
  "calling_prejoin_join_via_computer_audio_title": "Audio komputer",
  "calling_prejoin_computer_audio_content_aria_description": "Kontrol mikrofon dan speaker komputer",
  "calling_prejoin_join_via_no_audio_content": "Bergabung dengan suara dimatikan untuk menghindari gangguan audio.",
  "calling_prejoin_join_via_no_audio_subtitle": "Kami akan mematikan suara perangkat Anda saat bergabung.",
  "calling_prejoin_join_via_no_audio_speaker_detected_subtitle": "Anda berada di ruangan yang sudah memiliki audio rapat.",
  "calling_prejoin_join_via_no_audio_aria_desribedBy": "Tidak ada audio",
  "calling_prejoin_join_via_no_audio_title": "Jangan gunakan audio",
  "calling_prejoin_join_via_phone_audio_content": "Kami akan memberi nomor untuk menelepon setelah Anda bergabung, atau kami dapat menelepon Anda.",
  "calling_prejoin_join_via_phone_audio_subtitle": "Lakukan panggilan dari telepon mana pun, atau kami akan menghubungi Anda.",
  "calling_prejoin_join_via_phone_audio_loading_pstn_subtitle": "Memeriksa informasi panggilan masuk...",
  "calling_prejoin_join_via_phone_audio_title": "Audio telepon",
  "calling_prejoin_join_via_room_audio_subtitle": "Menggunakan sistem audio ruangan rapat.",
  "calling_prejoin_join_via_room_audio_title": "Audio ruangan",
  "calling_prejoin_join_via_room_audio_adjacent_room_detected_subtitle": "Kami mendeteksi perangkat ruang di sekitar.",
  "calling_prejoin_audio_option_suggested_title": "(disarankan)",
  "calling_prejoin_audio_options_more_details_instructions": "Tekan tab untuk opsi lainnya",
  "calling_prejoin_camera_toggle_title": "Kamera",
  "calling_prejoin_mic_toggle_title": "Mikrofon",
  "calling_mute_win": "Matikan suara (Ctrl+Shift+M)",
  "calling_mute_mac": "Bisukan (⌘+Shift+M)",
  "calling_unmute_win": "Nyalakan suara (Ctrl+Shift+M)",
  "calling_unmute_mac": "Nyalakan suara (⌘+Shift+M)",
  "calling_prejoin_blur_start": "Buramkan latar belakang saya",
  "calling_prejoin_blur_stop": "Jangan buramkan latar belakang",
  "calling_prejoin_background_filters_text": "Filter latar belakang",
  "calling_prejoin_join_button_label": "Gabung",
  "calling_prejoin_join_button_devices": "Menggunakan {{deviceName}}",
  "calling_prejoin_join_button_camera_on": "Kamera aktif",
  "calling_prejoin_join_button_camera_off": "Kamera nonaktif",
  "calling_prejoin_v2_join_button_camera_on": "Dengan kamera aktif dan",
  "calling_prejoin_v2_join_button_camera_off": "Dengan kamera tidak aktif dan",
  "calling_prejoin_join_button_mic_on": "Mikrofon aktif",
  "calling_prejoin_join_button_mic_off": "Mikrofon nonaktif",
  "calling_prejoin_mic_turned_on": "Mikrofon aktif",
  "calling_prejoin_mic_turned_off": "Mikrofon nonaktif",
  "calling_prejoin_v2_join_button_mic_on": "Mikrofon aktif",
  "calling_prejoin_v2_join_button_mic_off": "Mikrofon mati",
  "calling_prejoin_join_button_blur_on": "Buramkan latar belakang aktif",
  "calling_prejoin_join_button_blur_off": "Buramkan latar belakang nonaktif",
  "calling_custom_audience_organizer_tooltip": "Penyelenggara akan duduk terpisah dari peserta lain.",
  "calling_custom_audience_max_capacity_tooltip": "Mendukung hingga {{size}} video.",
  "calling_custom_audience_scene_selected": "{{imageName}} dipilih.",
  "calling_custom_video_backgrounds_none": "Tidak ada",
  "calling_custom_video_backgrounds_blur": "Buramkan",
  "calling_custom_video_backgrounds_selected": "{{imageName}} dipilih",
  "calling_custom_video_backgrounds_failed_to_load": "Gagal memuat",
  "calling_custom_video_backgrounds_add_new": "Tambah baru",
  "calling_custom_video_backgrounds_remove": "Hapus",
  "calling_custom_video_backgrounds_add_failed": "Tidak dapat menambahkan latar belakang",
  "calling_custom_video_backgrounds_delete_failed": "Tidak dapat menghapus latar belakang",
  "calling_custom_video_backgrounds_apply_failed": "Tidak dapat menerapkan latar belakang",
  "calling_custom_video_backgrounds_preview": "Pratinjau latar belakang",
  "calling_custom_video_backgrounds_stop_preview": "Hentikan pratinjau latar belakang",
  "calling_prejoin_settings_button_open": "Buka pengaturan perangkat",
  "calling_prejoin_settings_button_close": "Tutup pengaturan perangkat",
  "calling_prejoin_camera_not_available": "Kamera tidak tersedia",
  "calling_prejoin_connecting_header_aria_label": "Menyambung ke rapat",
  "calling_prejoin_connecting_with_room_aria_label_prefix": "Menyambungkan ke rapat dan memanggil {{roomDisplayName}}",
  "calling_prejoin_mic_not_available": "Mikrofon tidak tersedia",
  "calling_prejoin_blur_not_available": "Aktifkan video untuk efek buram",
  "calling_prejoin_device_troubleshoot": "Buka pengaturan perangkat untuk memecahkan masalah",
  "calling_prejoin_content_only_join": "Bergabung dengan audio nonaktif",
  "calling_prejoin_pstn_join": "Bergabung dengan telepon audio",
  "calling_meeting_audio_dialog_pstn_disconnected": "Anda terputus dari audio rapat ini.",
  "calling_meeting_details_agenda": "Agenda",
  "calling_meeting_details_description": "Deskripsi",
  "calling_meeting_details_agenda_duration_mf": "{totalMin, plural, =0{} other{#m}}",
  "calling_meeting_details_invite_link_text": "Bergabung dengan rapat Teams",
  "calling_meeting_options_button_ubar": "Opsi rapat",
  "calling_prejoin_room_join": "Gabung dan tambahkan ruang",
  "devices_content_only_message_link": "Anda sedang menonton tanpa suara. Untuk pengalaman sepenuhnya <0></0>",
  "devices_content_only_action_message": "aktifkan audio rapat",
  "calling_prejoin_automute_tooltip": "Sudah ada {{participantsCount}} orang dalam rapat. Kami telah mematikan suara mikrofon Anda.",
  "calling_prejoin_add_room_banner_close_button": "Tutup informasi ruang",
  "calling_prejoin_default_instant_channel_meeting_title": "Rapat saluran baru",
  "calling_scd_button_start_label": "Salin teks dan buka tautan di konten bersama",
  "calling_scd_button_stop_label": "Keluar dari pemindaian berbagi layar",
  "calling_scd_button_action_exit_interaction": "Keluar dari pemindaian",
  "screen_content_digitizer_loader_message": "Memindai berbagi layar...",
  "screen_content_digitization_live_content_label": "LANGSUNG",
  "calling_prejoin_v2_landing_announcement": "Pilih opsi video dan audio Anda untuk {{meetingTitle}}",
  "calling_share_button_stop_sharing_aria_label_win": "Berhenti berbagi (Ctrl+Shift+E)",
  "calling_share_button_open_sharetray_aria_label_win": "Bagikan konten (Ctrl+Shift+E)",
  "calling_share_button_close_sharetray_aria_label_win": "Sembunyikan opsi berbagi (Ctrl+Shift+E)",
  "calling_share_button_stop_sharing_aria_label_mac": "Berhenti berbagi (⌘+Shift+E)",
  "calling_share_button_open_sharetray_aria_label_mac": "Bagikan konten (⌘+Shift+E)",
  "calling_share_button_close_sharetray_aria_label_mac": "Sembunyikan opsi berbagi (⌘+Shift+E)",
  "calling_staging_room_start_meeting_button": "Mulai rapat",
  "calling_start_recording_and_transcript": "Mulai perekaman dan transkripsi",
  "calling_switch_to_gallery_mode_confirmation_aria": "Mode galeri ditetapkan",
  "calling_switch_to_large_gallery_mode_confirmation_aria": "Mode galeri besar ditetapkan",
  "calling_switch_to_together_mode_confirmation_aria": "Mode bersama ditetapkan",
  "calling_together_mode_assign_seats": "Tetapkan kursi",
  "calling_together_mode_setup": "Penyiapan mode Bersama",
  "calling_together_mode_setup_selected": "Penyiapan mode Bersama telah dipilih",
  "calling_enter_gallery_on_top_mode": "Mode galeri di paling atas telah ditetapkan",
  "calling_exit_gallery_on_top_mode": "Mode galeri di paling atas telah ditutup",
  "calling_enter_focus_mode": "Mode Fokus telah disetel",
  "calling_exit_focus_mode": "Mode Fokus telah ditutup",
  "calling_enter_content_only_layout": "Tata letak Hanya Konten sudah disetel",
  "calling_enter_people_only_layout": "Tata letak Hanya Orang sudah disetel",
  "calling_enter_content_and_people_layout": "Tata letak Konten + Orang sudah disetel",
  "calling_enter_fullscreen_mode": "Mode layar penuh telah disetel",
  "calling_exit_fullscreen_mode": "Mode layar penuh telah ditutup",
  "group_chat_with_federated_users_not_supported": "Tidak tersedia dalam obrolan grup yang berisi peserta eksternal.",
  "rtflyout_menu_title_transcript": "Transkripsi",
  "rtflyout_menu_title_recording": "Perekaman",
  "rtflyout_calling_start_recording_and_transcript": "Rekam dan transkripsikan",
  "rtflyout_calling_start_recording": "Rekam saja",
  "rtflyout_calling_start_transcript": "Transkripsi saja",
  "rtflyout_calling_stop_recording_confirmation_button_key": "Ya, hentikan",
  "rtflyout_calling_stop_transcription_confirmation_button_key": "Ya, hentikan",
  "rtflyout_calling_stop_recording_confirmation_dialog_text": "Anda dapat mulai merekam lagi jika berubah pikiran.",
  "rtflyout_calling_turnoff_recording_and_transcript": "Tidak Aktif",
  "rtflyout_calling_stop_transcription_confirmation_text": "Anda dapat memulainya lagi jika berubah pikiran.​",
  "rtflyout_calling_stop_recording_transcript_confirmation_text": "Anda dapat memulainya lagi jika berubah pikiran.",
  "rtflyout_calling_stop_transcript_confirmation_dialog_title": "Hentikan transkripsi?",
  "rtflyout_calling_stop_recording_transcript": "Ya, hentikan",
  "rtflyout_calling_stop_transcript": "Hentikan transkripsi",
  "calling_stop_recording_and_transcript": "Hentikan perekaman dan transkripsi.",
  "calling_recording_transcript_not_allowed_tooltip": "Hanya penyelenggara rapat dan penyaji yang dapat memulai perekaman dan transkripsi",
  "calling_recording_not_allowed_freemium_tooltip": "Tidak tersedia di Teams gratis",
  "calling_stop_recording_transcript_confirmation_text": "Rapat ini direkam dan ditranskripsi. Anda yakin ingin berhenti?",
  "calling_stop_recording_transcript_confirmation_dialog_title": "Hentikan perekaman dan transkripsi?",
  "calling_stop_recording_transcript": "Hentikan perekaman dan transkripsi.",
  "calling_change_view_mode_button_tooltip_gallery": "Tampilan Galeri. Klik untuk mengubah",
  "calling_change_view_mode_button_tooltip_large_gallery": "Tampilan galeri besar. Klik untuk mengubah",
  "calling_change_view_mode_button_tooltip_audience": "Mode Bersama. Klik untuk mengubah",
  "calling_change_view_mode_button_tooltip_content_and_people": "Konten + Orang. Klik untuk mengubah",
  "calling_change_view_mode_button_tooltip_content_only": "Hanya Konten. Klik untuk mengubah",
  "calling_change_view_mode_button_tooltip_one_to_one": "Ubah tampilan",
  "calling_switch_audience": "Mode Bersama (Pratinjau)",
  "calling_switch_audience_without_preview": "Mode bersama",
  "calling_switch_grid": "Galeri",
  "calling_switch_large_grid": "Galeri besar",
  "calling_switch_audience_badgeText_default": "Berbagi ruang maya dengan orang lain",
  "calling_switch_audience_badgeText_expanded": "Berbagi ruang maya dengan {{configThresholdNumber}} atau lebih banyak orang",
  "calling_switch_audience_badgeText_disabled_due_to_host_view_mode": "Tidak tersedia saat rapat berada dalam Mode terkelola.",
  "calling_switch_large_grid_badgeText_default": "Tampilkan hingga 49 video sekaligus",
  "calling_switch_large_grid_badgeText_disabled_due_to_host_view_mode": "Tidak tersedia saat rapat berada dalam Mode terkelola.",
  "calling_switch_large_grid_badgeText_expanded": "Tampilkan lebih dari {{configThresholdNumber}} video sekaligus",
  "calling_switch_large_grid_aria": "Galeri besar",
  "calling_switch_audience_aria": "Mode bersama",
  "calling_transcript_message_aria_label": "Tekan enter untuk membuka transkripsi rapat",
  "calling_ubar_ppt_back_to_presenter": "Untuk penyaji: {{presenterSlideText}}",
  "calling_ubar_ppt_slide_number": "{{currentPosition}} dari {{slidesCount}}",
  "calling_ubar_ppt_sharing_layout_label": "Mode penyaji",
  "calling_other_participants_region": "Peserta lain",
  "calling_share_meeting_invite_dialog_get_link_error": "Tidak bisa mendapatkan tautan rapat.\nCoba lagi nanti.",
  "calling_dominant_speakers_region": "Speaker aktif",
  "calling_call_ended_cqf_announcement": "Panggilan berakhir, {{cqfTitle}} Tekan tombol tab untuk menilai panggilan.",
  "calling_call_ended_cqf_short_call_announcement": "Panggilan berakhir, {{cqfTitle}} Tekan tombol tab untuk memilih alasannya",
  "calling_call_controls_region": "Kontrol rapat",
  "calling_call_recordings_load_error": "Terjadi kesalahan saat mengambil rekaman panggilan, coba lagi.",
  "calling_screensharing_recording_disabled_popover_inner_text": "Keamanan & Privasi > Perekaman Layar",
  "calling_screensharing_recording_disabled_popover_outer_text": "Buka <0></0> untuk memberikan izin dan mulai berbagi.",
  "calling_content_sharing_preview_screen_camera_dropdown_title": "Kamera",
  "calling_content_camera_setup_dialog_camera_consent_title": "Anda perlu mengaktifkan kamera untuk memindai papan tulis.",
  "calling_content_camera_setup_dialog_camera_on_button_title": "Aktifkan kamera",
  "calling_content_camera_preview_whiteboard_title": "Berbagi papan tulis",
  "calling_content_camera_preview_document_title": "Berbagi dokumen",
  "calling_content_camera_preview_whiteboard_subtitle": "Arahkan kamera ke papan tulis terdekat untuk mendeteksi.",
  "calling_content_camera_preview_document_subtitle": "Tampilkan dokumen melalui kamera dokumen atau kamera web Anda.",
  "calling_content_camera_preview_whiteboard_subtitle_with_me_video": "Arahkan kamera ke papan tulis terdekat untuk mendeteksi. Kami akan menghentikan berbagi video saat Anda melakukan hal ini.",
  "calling_content_camera_preview_document_subtitle_with_me_video": "Tampilkan dokumen melalui kamera dokumen atau kamera web Anda. Kami akan menghentikan berbagi video saat Anda melakukan hal ini.",
  "calling_content_camera_preview_button_title": "Mengerti",
  "calling_content_camera_preview_camera_dropdown_tooltip": "Untuk pengalaman terbaik, gunakan headphone nirkabel dan kamera dengan resolusi setidaknya 720p.",
  "calling_device_has_been_selected_content_scan_preview": "{{deviceName}} dipilih",
  "calling_content_sharing_preview_footer": "Pratinjau pribadi",
  "calling_content_sharing_preview_footer_v2": "Pratinjau",
  "calling_content_camera_preview_document_toast_message": "Mencari dokumen",
  "calling_content_camera_preview_whiteboard_toast_message": "Mencari papan tulis",
  "calling_content_camera_preview_document_error_toast_message": "Tidak dapat mendeteksi tepi. Kami telah menonaktifkan deteksi tepi, tetapi Anda masih dapat berbagi dokumen.",
  "calling_content_camera_preview_whiteboard_error_toast_message": "Tidak dapat mendeteksi tepi. Kami telah menonaktifkan deteksi tepi, tetapi Anda masih dapat berbagi papan tulis.",
  "calling_content_sharing_preview_footer_with_description": "<0></0> (hanya Anda yang dapat melihat ini)",
  "calling_content_sharing_controls_region": "Kontrol berbagi konten",
  "calling_coachmark_share_content": "Gunakan kamera apa pun untuk berbagi dokumen, papan tulis fisik, dan banyak lagi.",
  "screensharing_started_announcement": "{{name}} telah berbagi layar di Teams.",
  "screensharing_started_anonymous_announcement": "Seseorang telah berbagi layar dalam Teams.",
  "stop_all_spotlights": "Hentikan semua sorotan",
  "stop_all_spotlights_announcement": "Semua sorotan dihentikan",
  "spotlight_participant_stream": "Soroti untuk semua orang?",
  "spotlight_add_participant_stream": "Tambahkan sorotan",
  "spotlight_myself": "Soroti saya",
  "cancel_spotlight_participant_stream": "Hentikan penyorotan",
  "cancel_self_spotlight_participant_stream": "Keluar sorotan",
  "spotlight_participant_tooltip": "Soroti video ini untuk semua peserta rapat",
  "spotlight_participant_limit_reached_tooltip": "Tidak ada lagi orang yang dapat disorot",
  "stop_spotlight_participant_tooltip": "Hentikan menyoroti video ini untuk semua peserta rapat",
  "spotlight_started_announcement": "{{name}} sedang disorot.",
  "spotlight_stopped_announcement": "{{name}} tidak disorot lagi.",
  "spotlight_active_me_tooltip": "Video Anda disorot untuk semua orang dalam rapat.",
  "spotlight_active_participant_tooltip": "Video peserta disorot untuk semua orang dalam rapat.",
  "spotlight_confirm_start_dialog_title": "Soroti untuk semua orang?",
  "spotlight_confirm_start_dialog_text": "Anda akan menyorot video ini untuk semua peserta rapat.",
  "spotlight_confirm_start_self_dialog_text": "Anda akan menyorot video Anda untuk semua orang dalam rapat.",
  "spotlight_confirm_stop_dialog_title": "Berhenti menyorot video ini?",
  "spotlight_confirm_stop_all_dialog_title": "Hentikan penyorotan semua video?",
  "spotlight_confirm_stop_self_dialog_title": "Keluar sorotan?",
  "spotlight_confirm_stop_dialog_text": "Video tidak akan lagi disorot untuk semua orang dalam rapat.",
  "spotlight_confirm_stop_all_dialog_text": "Video tidak akan lagi disorot untuk semua orang dalam rapat.",
  "spotlight_confirm_stop_self_dialog_text": "Video Anda tidak akan lagi disorot untuk semua orang dalam rapat.",
  "pin_participant_tooltip": "Sematkan video ini ke tampilan Anda",
  "pin_myself_tooltip": "Sematkan video Anda",
  "pin_myself": "Sematkan saya",
  "unpin_myself": "Lepas sematan saya",
  "call_leave": "Keluar",
  "call_lobby_admit_aria": "Izinkan masuk peserta {{name}} dari lobi",
  "call_lobby_close_notification": "Tutup pemberitahuan",
  "call_participant_left": "{{name}} meninggalkan rapat",
  "calling_participant_has_video_token": "video aktif",
  "calling_participant_is_muted_token": "dibisukan",
  "calling_participant_is_hand_raised_token": "tangan diacungkan",
  "calling_participant_is_pinned_token": "disematkan",
  "calling_participant_is_spotlighted_token": "disorot",
  "calling_participant_is_weatherperson_token": "dalam mode presentasi",
  "calling_participant_screensharing_weatherperson": "Konten dibagikan oleh {{sharer}} dalam mode presentasi",
  "calling_participant_was_pinned_confirmation": "Peserta disematkan",
  "calling_participant_was_unpinned_confirmation": "Sematan peserta dilepas",
  "calling_participant_aria_label_template_1": "{{name}}, {{token1}}",
  "calling_participant_aria_label_template_2": "{{name}}, {{token1}}, {{token2}}",
  "calling_participant_aria_label_template_3": "{{name}}, {{token1}}, {{token2}}, {{token3}}",
  "calling_participant_aria_label_template_4": "{{name}}, {{token1}}, {{token2}}, {{token3}}, {{token4}}",
  "calling_participant_aria_label_template_5": "{{name}}, {{token1}}, {{token2}}, {{token3}}, {{token4}}, {{token5}}",
  "calling_call_ended_questionnaire_announcement": "Panggilan berakhir, {{questionnaireTitle}} Tekan tombol tab untuk menilai panggilan.",
  "calling_option_selected_announcement": "{{selectedOption}} dipilih.",
  "calling_participant_aria_label_template_6": "{{name}}, {{token1}}, {{token2}}, {{token3}}, {{token4}}, {{token5}}, {{token6}}",
  "calling_viva_emf_title": "{{name}} telah meminta umpan balik untuk rapat ini",
  "calling_viva_emf_title_no_organizer": "Penyelenggara telah meminta umpan balik untuk rapat ini",
  "calling_viva_emf_effective_title": "Seberapa efektif pelaksanaan rapat ini dalam mencapai tujuan bisnis?",
  "calling_viva_emf_privacy_statement": "Penyelenggara rapat hanya akan melihat hasil agregat dan tidak akan memiliki tampilan siapa yang memberikan respons.",
  "calling_viva_emf_privacy_statement_link": "Pernyataan privasi",
  "calling_viva_emf_error_label": "Maaf, terjadi kesalahan.",
  "calling_emf_submit_button": "Kirim",
  "calling_emf_title_with_privacy": "Bantu meningkatkan rapat di Microsoft. Survei ini sepenuhnya opsional. Respons tidak akan terkait dengan informasi pribadi Anda.",
  "calling_emf_title": "Bantu sempurnakan rapat di Microsoft",
  "calling_emf_questionnaire_title": "Apa yang akan menjadikannya lebih baik?",
  "calling_emf_questionnaire_before_meeting_subtitle": "Sebelum rapat",
  "calling_emf_questionnaire_before_meeting_subtitle_aria_label": "Apa yang akan membuatnya lebih baik sebelum rapat?",
  "calling_emf_questionnaire_during_meeting_subtitle": "Selama rapat",
  "calling_emf_questionnaire_during_meeting_subtitle_aria_label": "Apa yang akan membuatnya lebih baik selama rapat?",
  "calling_emf_effective_title": "Seberapa efektif pelaksanaan rapat ini dalam mencapai tujuan bisnis?",
  "calling_empty_call_history": "Saat Anda melakukan atau menerima panggilan, kami mencantumkannya di sini.",
  "calling_emf_inclusive_title": "Sejauh mana Anda merasa disertakan dalam rapat ini?",
  "calling_emf_privacy_notice_link": "Pemberitahuan Perlindungan Data Microsoft",
  "calling_emf_volunteer_notice": "Survei ini sepenuhnya opsional.",
  "calling_emf_personal_data": "Respons tidak akan terkait dengan informasi pribadi Anda.",
  "calling_emf_cancel_button": "Batal",
  "calling_emf_continue_button": "Lanjutkan",
  "calling_cqf_item_including_agenda": "Agenda",
  "calling_cqf_item_define_goals": "Tujuan ditentukan",
  "calling_cqf_item_define_roles": "Peran ditentukan",
  "calling_cqf_item_provide_preread": "Materi disediakan sebelumnya",
  "calling_cqf_item_including_everyone_involved": "Lebih banyak orang yang disertakan",
  "calling_cqf_item_including_fewer_participants": "Mengundang lebih sedikit peserta",
  "calling_cqf_item_more_participation": "Lebih banyak orang yang berkontribusi",
  "calling_cqf_item_more_attendee_participation": "Lebih banyak orang yang berkontribusi",
  "calling_cqf_item_more_attendee_video": "Lebih banyak orang yang menggunakan video",
  "calling_cqf_item_better_audio_video_quality": "Kualitas audio atau video yang lebih baik",
  "calling_cqf_item_better_time_management": "Manajemen waktu yang lebih baik",
  "calling_cqf_item_more_inclusive_and_tone": "Bahasa yang lebih sopan dan inklusif",
  "calling_cqf_item_more_remote_participation": "Lebih banyak kontribusi dari orang jarak jauh",
  "calling_cqf_item_clearer_articulation_action_items": "Langkah berikutnya yang lebih jelas",
  "calling_cqf_item_include_agenda": "Termasuk notula dan peran",
  "calling_cqf_item_send_premeeting_reading": "Mengirim bacaan untuk mempersiapkan rapat",
  "calling_cqf_item_time_management": "Manajemen waktu yang lebih baik",
  "calling_cqf_item_voice_tone": "Pilihan kata dan nada suara yang lebih baik",
  "calling_cqf_item_include_required_participants": "Partisipasi semua peserta yang wajib hadir",
  "calling_cqf_item_remote_participant": "Kemampuan yang lebih baik bagi peserta jarak jauh untuk berpartisipasi dan berbicara",
  "calling_cqf_item_audio_video_quality": "Kualitas audio/video yang lebih baik",
  "calling_cqf_item_audio_video_reliablity": "Keandalan audio/video yang lebih baik",
  "calling_cqf_item_more_video": "Lebih banyak orang yang menggunakan video",
  "calling_cqf_item_emf_other": "Lainnya, harap sebutkan",
  "calling_emf_rating_description_1": "Sangat tidak efektif",
  "calling_emf_rating_description_2": "Tidak efektif",
  "calling_emf_rating_description_3": "Tidak keduanya, baik efektif maupun tidak efektif",
  "calling_emf_rating_description_4": "Efektif",
  "calling_emf_rating_description_5": "Sangat efektif",
  "calling_emf_inclusive_rating_description_1": "Sangat tidak inklusif",
  "calling_emf_inclusive_rating_description_2": "Tidak inklusif",
  "calling_emf_inclusive_rating_description_3": "Tidak keduanya, baik inklusif maupun tidak inklusif",
  "calling_emf_inclusive_rating_description_4": "Inklusif",
  "calling_emf_inclusive_rating_description_5": "Sangat inklusif",
  "calling_emf_effective_rating_description_1": "Tidak efektif sama sekali",
  "calling_emf_effective_rating_description_2": "Tidak efektif",
  "calling_emf_effective_rating_description_3": "Tidak keduanya, baik efektif maupun tidak efektif",
  "calling_emf_effective_rating_description_4": "Efektif",
  "calling_emf_effective_rating_description_5": "Sangat efektif",
  "calling_emf_incl_rating_description_1": "Tidak disertakan sama sekali",
  "calling_emf_incl_rating_description_2": "Tidak disertakan",
  "calling_emf_incl_rating_description_3": "Tidak keduanya, baik disertakan maupun dikecualikan",
  "calling_emf_incl_rating_description_4": "Disertakan",
  "calling_emf_incl_rating_description_5": "Sangat disertakan",
  "star_ratings_description": "Opsi peringkat",
  "call_transcript_not_allowed_tooltip": "Tidak tersedia dalam rapat ini",
  "call_transcript_not_allowed_capabilities": "Tidak tersedia dalam rapat ini",
  "call_transcript_not_allowed_meeting_organizer": "Dinonaktifkan oleh penyelenggara",
  "call_transcript_not_allowed_attendee_tooltip": "Hanya penyelenggara rapat dan penyaji yang dapat memulai transkripsi",
  "call_transcript_not_allowed_organization": "Organisasi Anda tidak mengizinkan transkripsi",
  "call_transcript_not_allowed_federated_tooltip": "Tidak tersedia untuk orang di organisasi yang berbeda dari penyelenggara",
  "call_transcript_not_allowed_guest_tooltip": "Tamu tidak dapat memulai transkripsi",
  "call_transcript_not_allowed_anonymous_tooltip": "Masuk ke Teams untuk memulai transkripsi",
  "call_transcript_not_allowed_waiting": "Transkripsi dimulai...",
  "call_transcript_not_allowed_disabled": "Tunggu...",
  "lobby_popup_admitting": "Mengizinkan",
  "lobby_popup_participants": "{{name}} dan {{numberOfOtherParticipants}}",
  "aria_announce_lobby_participants_mf": "{number, plural, =1{{participantsInLobby} sedang menunggu di lobi. Tekan {hotkey} untuk memasukkannya.} =2{{participantsInLobby} lainnya menunggu di lobi. } other{{participantsInLobby} lainnya menunggu di lobi.}}",
  "aria_announce_call_on_hold_state": "Anda menahan panggilan",
  "aria_announce_call_resume_state": "Panggilan dilanjutkan",
  "calling_forwarding_status": "Mengalihkan panggilan",
  "copied_meeting_info": "Disalin",
  "calling_toggle_music_mode_off": "Nonaktifkan mode audio ketepatan tinggi",
  "calling_toggle_music_mode_on": "Aktifkan mode audio ketepatan tinggi",
  "aria_announce_more_participant_joined_mf": "{number, plural, =1{{participantName} bergabung ke panggilan} other{ # lebih banyak peserta bergabung ke panggilan}}",
  "aria_announce_participant_joined_call": "Anda telah bergabung dengan panggilan",
  "aria_announce_participant_joined_meeting": "Anda telah bergabung dengan rapat",
  "aria_announce_participants_in_call_mf": "{number, plural, =0{Anda satu-satunya yang ada di sini} =1{{name1} sedang melakukan panggilan} =2{{name1}, {name2} sedang dalam panggilan} other{ # peserta lainnya dalam panggilan}}",
  "aria_label_content_only_button": "Opsi bergabung lainnya. Gabung dengan audio nonaktif.",
  "aria_label_switch_camera_button": "Beralih kamera",
  "switch_camera_button_tooltip": "Beralih kamera",
  "shortcut_admit_lobby_participant": "Masukkan peserta yang ditampilkan di lobby toast.",
  "calling_screen_lobby_participants_waiting_in_lobby_mf": "{number, plural, =1{menunggu di lobi.} other{menunggu di lobi.}}",
  "aria_calling_breakout_room_participants_in_room_mf": "{number, plural, =0{Ruangan ini kosong.} =1{{number} peserta.} other{{number} peserta.}}",
  "aria_calling_breakout_room_state": "Status saat ini: {{state}}",
  "aria_calling_breakout_room_select_all": "Pilih semua atau beberapa peserta dari daftar dan tekan Shift F10 untuk melihat daftar penetapan ruangan.",
  "calling_camera_turned_off": "Kamera Anda dinonaktifkan",
  "calling_camera_turned_on": "Kamera Anda diaktifkan",
  "calling_camera_not_connected": "Kamera tidak tersambung",
  "calling_camera_better_together_mode": "Pratinjau video tidak tersedia",
  "calling_hard_mute_mic_enabled_for_attendee": "Mikrofon Anda telah diaktifkan. Nyalakan suara jika Anda ingin berbicara.",
  "calling_roster_header_hard_mute_dialog_content_msg": "Peserta tidak dapat menyalakan suara sendiri.",
  "calling_roster_header_hard_mute_dialog_content_without_raise_hand": "Penyelenggara rapat dan penyaji dapat mengizinkan peserta menyalakan suara seperlunya.",
  "calling_roster_header_hard_mute_dialog_content_with_raise_hand": "Jika seorang mengangkat tangan, penyaji dapat memungkinkan mereka menyalakan suaranya.",
  "calling_mic_muted": "Suara mikrofon Anda dimatikan",
  "calling_mic_unmuted": "Mikrofon Anda dinyalakan suaranya",
  "calling_microsoft_whiteboard_loading": "Microsoft Whiteboard sedang dimuat",
  "calling_whiteboard_not_shared": "Papan tulis tidak lagi dibagikan",
  "calling_speaker_off": "Speaker nonaktif",
  "calling_speaker_on": "Speaker aktif",
  "calling_speaker_turned_off": "Speaker dinonaktifkan",
  "calling_speaker_turned_on": "Speaker diaktifkan",
  "calling_alert_speaking_while_muted": "Anda dibisukan.",
  "calling_alert_suggest_unmuting_win": "Tekan Ctrl+Shift+M untuk menyalakan suara mikrofon Anda.",
  "calling_alert_suggest_unmuting_mac": "Tekan ⌘+Shift+M untuk menyalakan suara mikrofon Anda.",
  "calling_alert_suggest_unmuting_push_to_talk_win": "Tekan Ctrl+Shift+M untuk menyalakan suara mikrofon, atau tekan dan tahan Tombol Spasi untuk menyalakan suara sementara waktu.",
  "calling_alert_suggest_unmuting_push_to_talk_mac": "Tekan ⌘+Shift+M untuk menyalakan suara mikrofon, atau tekan dan tahan Tombol Spasi untuk menyalakan suara sementara waktu.",
  "calling_alert_speaking_while_muted_announcement": "Anda berbicara saat mikrofon dibisukan. {{suggestedAction}}",
  "calling_alert_suggest_unmuting_announcement_win": "Tekan Ctrl+Shift+M untuk menyalakan suara.",
  "calling_alert_suggest_unmuting_announcement_mac": "Tekan ⌘+Shift+M untuk menyalakan suara.",
  "calling_alert_temporarily_unmuted": "Suara Anda dinyalakan.",
  "calling_alert_suggest_muting_back": "Lepaskan Bilah Spasi untuk mematikan suara mikrofon lagi.",
  "calling_alert_temporarily_unmuted_announcement": "Suara Anda dinyalakan. {{suggestedAction}}",
  "calling_alert_transcription_language_changed": "Bahasa lisan diatur ke {{newSpokenLanguage}}",
  "calling_alert_coach_private_notification": "Kepada Anda: {{coachContent}}",
  "calling_alert_mute_coach_tooltip": "Bisukan Pemberitahuan Pelatih",
  "call_toggle_speaker_button": "{{status}} speaker",
  "call_toggle_microphone_button": "{{status}} mikrofon",
  "call_volume_slider_aria_label": "Kontrol Volume speaker",
  "calling_merge_calls_list_item_header": "Panggil dengan",
  "calling_merge_calls_dialog_title": "Pilih panggilan yang akan digabung",
  "calling_merge_calls_dialog_cancel": "Batal",
  "calling_merge_calls_dialog_confirm": "Gabung",
  "calling_merge_calls_ubar_button_title": "Gabungkan Panggilan",
  "calling_confirm_audio_escalation_dialog_call_content": "Tindakan ini akan mengaktifkan mikrofon dan speaker komputer Anda. Jika ponsel di sekitar atau perangkat audio lain sedang dalam panggilan, Anda dapat menyebabkan gema.",
  "calling_confirm_audio_escalation_dialog_meeting_content": "Ini akan mengaktifkan mikrofon dan speaker komputer Anda. Jika ponsel terdekat atau perangkat audio lainnya sudah ada dalam rapat, Anda dapat menyebabkan gema.",
  "companion_selection_screen_call_type": "panggil",
  "companion_selection_screen_meeting_type": "rapat",
  "companion_selection_screen_title": "Anda sudah berada dalam {{screenType}} ini di perangkat lain.",
  "companion_selection_add_device": "Tambahkan perangkat ini",
  "companion_selection_transfer": "Transfer ke perangkat ini",
  "companion_selection_add_device_content": "Bergabung dengan suara dimatikan dan simpan perangkat lainnya dalam {{screenType}}.",
  "companion_selection_transfer_content": "Gunakan perangkat ini saja untuk {{screenType}}.",
  "copy_meeting_entry_info_tooltip_disabled_registration": "Informasi bergabung tidak dapat dibagikan untuk acara yang memerlukan pendaftaran",
  "share_content": "Bagikan konten",
  "present_content": "Sajikan",
  "screen_sharing_options_aria_label": "Bagikan layar, jendela, atau tab",
  "screen_sharing_options": "Layar, jendela, atau tab",
  "screen_sharing_options_description": "Pilih yang ingin Anda bagikan",
  "content_share_whiteboard_subtitle": "Berkolaborasi di papan tulis",
  "share_tray_panel_show_more": "Lainnya",
  "share_tray_panel_show_more_aria_label": "Layar Lainnya",
  "share_tray_panel_windows_aria_label": "Membuka daftar {{windowsCount}} jendela aktif",
  "share_tray_panel_screens_title": "Layar",
  "share_tray_panel_windows_title": "Jendela",
  "share_tray_panel_whiteboard_title": "Papan Tulis",
  "share_tray_ppt_content_title": "PowerPoint Live",
  "share_tray_ppt_content_subtitle": "Lihat catatan, slide, dan audiens saat Anda menyajikan presentasi",
  "share_tray_back_button_tooltip": "Kembali untuk berbagi konten utama baki",
  "non_image_screen_preview_text": "Layar {{screenNumber}}",
  "share_audio": "Sertakan suara komputer",
  "share_audio_disable_tooltip": "Tingkatkan ke versi macOS 10.13 atau yang lebih baru untuk menggunakan fitur ini.",
  "sharing_layout_content_only_button": "Hanya konten",
  "sharing_layout_header": "Mode penyaji",
  "sharing_layout_newsanchor_button": "Reporter",
  "sharing_layout_sidebyside_button": "Berdampingan",
  "sharing_layout_weatherperson_button": "Menonjol",
  "sharing_layout_toolbar_aria_label": "Mode penyaji",
  "sharing_layout_video_disabled_tooltip": "Aktifkan kamera untuk memilih tata letak ini",
  "sharing_layout_custom_background_button_label": "Sesuaikan",
  "sharing_layout_custom_background_error_message": "Gagal menerapkan latar belakang, coba lagi.",
  "sharing_layout_custom_background_list_label": "Kustomisasi latar belakang",
  "toggle_scd": "Perbolehkan interaksi",
  "video_background_settings_preview_is_on": "Pratinjau video aktif.",
  "video_background_settings_preview_is_off": "Pratinjau video nonaktif.",
  "video_background_settings_preview_action_tooltip_mirrored": "Orang lain akan melihat gambar ini terbalik.",
  "calling_prejoin_search_for_room_placeholder": "Mencari ruangan",
  "calling_prejoin_info_search_for_room_description": "Untuk ini, Sistem Ruangan Teams perlu menjadi bagian dari organisasi Anda.",
  "calling_prejoin_no_rooms_found": "Tidak dapat menemukan ruangan",
  "calling_prejoin_info_selected_room": "Kami akan menambahkan sistem audio ruangan ke rapat setelah Anda bergabung",
  "calling_camera_effects_title": "Efek video",
  "calling_video_effects_title": "Efek video",
  "calling_camera_effects_backgrounds_header": "Latar Belakang",
  "calling_camera_effects_filters_header": "Filter",
  "calling_camera_effects_auto_adjust_label": "Koreksi ringan",
  "calling_camera_effects_auto_adjust_toggle_off": "Koreksi cahaya nonaktif",
  "calling_camera_effects_auto_adjust_toggle_on": "Koreksi cahaya aktif",
  "calling_camera_effects_auto_adjust_description": "Menyesuaikan tingkat cahaya di video secara otomatis.",
  "calling_camera_effects_touch_up_label": "Perbaiki tampilan saya",
  "calling_camera_effects_touch_up_toggle_off": "Perbaikan tidak aktif",
  "calling_camera_effects_touch_up_toggle_on": "Perbaikan aktif",
  "call_touch_up_strength_slider_aria_label": "Kontrol intensitas perbaikan",
  "error_retrieving_voice_admin_settings": "Kesalahan mengambil Pengaturan Panggilan",
  "no_device_selected": "Tidak Ada Perangkat Dipilih",
  "forwarding_to_target": "Meneruskan ke {{target}}",
  "forward_to_target": "Teruskan ke {{target}}",
  "active_in_call_with": "sedang dalam panggilan dengan {{caller}}",
  "call_forwarding_off": "Jangan teruskan",
  "call_forwarding_to_voicemail": "Teruskan ke pesan suara",
  "call_forwarding_to_call_group": "Meneruskan ke grup panggilan",
  "forwarding_to_delegates": "Meneruskan ke delegasi",
  "forward_settings_menu_header": "Meneruskan",
  "call_group_settings": "Pengaturan grup panggilan",
  "call_group_added_mf": "{number, plural, =1 {Dalam 1 grup panggilan} other{Dalam # grup panggilan}}",
  "call_group_owners_header_mf": "{number, plural, =1{Grup panggilan} other{Grup panggilan}}",
  "calls_history": "Riwayat",
  "calls_shared_lines": "Saluran bersama",
  "edit_notifications": "Edit pemberitahuan",
  "more_calling_forwarding_settings": "Pengaturan lainnya",
  "hardware_out_in_use_device_description": "{{deviceName}} (sedang digunakan)",
  "hardware_out_in_use_device_by_user_name_description": "{{deviceName}} (sedang digunakan oleh {{userName}})",
  "hardware_out_device_current_resolution": "Resolusi: {{format}}",
  "hardware_out_device_start_button": "Mulai",
  "hardware_out_device_stop_button": "Berhenti",
  "hardware_out_menu_send_to_device_button": "Kirim video ke Perangkat Keras",
  "hardware_out_device_switch_button": "Alihkan",
  "show_pano_stream": "Tampilkan panorama",
  "hide_pano_stream": "Sembunyikan panorama",
  "dialpad_placeholder": "Ketikkan nama atau nomor telepon",
  "dialpad_placeholder_no_pstn": "Ketikkan nama",
  "start_call": "Panggil",
  "call_history_table_aria_label": "Tabel riwayat panggilan dan pesan suara",
  "call_park_pickup": "Parkir Panggilan",
  "calling_history_filter_label_all": "Semua",
  "calling_history_filter_label_missed": "Tak terjawab",
  "calling_history_filter_label_outgoing": "Keluar",
  "calling_history_filter_label_incoming": "Masuk",
  "calling_history_filter_label_forwarded": "Diteruskan",
  "calling_history_filter_label_attachments": "Lampiran",
  "calling_history_filter_button_title": "Filter",
  "calling_history_filter_input_placeholder": "Filter menurut nama atau nomor",
  "calling_history_filter_input_more_options_title": "Opsi lainnya",
  "calling_history_filter_input_close_title": "Tutup filter",
  "calling_history_filter_input_remove_title": "Hapus",
  "calling_history_label_incoming_call_queue": "Masuk untuk {{callQueueBotName}}",
  "calling_history_label_outgoing_call_queue": "Panggilan keluar {{callQueueBotName}}",
  "work_number": "Nomor kantor: {{phoneNumber}}",
  "safe_transfer_option_message": "Deringkan kembali jika tak ada jawaban.",
  "safe_transfer_option_disabled_message": "Deringkan kembali tidak tersedia untuk penerima ini.",
  "error_retrieving_policy": "Terjadi kesalahan saat mengambil kebijakan",
  "call_history_call_duration_long_mf": "{totalHour, plural, =0{}  other{#j}} {min, plural, =0{}  other{#m}}",
  "call_history_call_duration_short_mf": "{totalMin, plural, =0{} other{#m}} {sec, plural, =0{#d}  other{#d}}",
  "call_history_call_duration_long_with_aria_mf": "{totalHour, plural, =0{Durasi panggilan # jam}  other{Durasi panggilan # jam}} {min, plural, =0{# menit}  other{# menit}}",
  "call_history_call_duration_short_with_aria_mf": "{totalMin, plural, =0{Durasi panggilan # menit}  other{Durasi panggilan # menit}} {sec, plural, =0{# detik}  other{ # detik}}",
  "calling_full_screen": "Layar penuh",
  "shortcut_leave_call": "Keluar dari rapat atau panggilan.",
  "custom_setup": "Penyiapan Kustom",
  "audio_device_settings": "Pengaturan perangkat audio",
  "audio_device_settings_menu_header": "Perangkat Audio",
  "calling_delegate_avatar_subtitle": "Mendukung Anda",
  "calling_delegator_avatar_subtitle": "Anda mendukung",
  "banner_voicemail_fetching": "Memuat pesan suara Anda...",
  "dialpad_title": "Panggilan",
  "calling_stopVideo_win": "Nonaktifkan kamera (Ctrl+Shift+O)",
  "calling_stopVideo_mac": "Matikan kamera (⌘+Shift+O)",
  "calling_startVideo_win": "Aktifkan kamera (Ctrl+Shift+O)",
  "calling_startVideo_mac": "Aktifkan kamera (⌘+Shift+O)",
  "calling_hangup_win": "Keluar (Ctrl+Shift+B)",
  "calling_hangup_mac": "Keluar (tombol ⌘+Shift+B)",
  "calling_call_as_yourself": "Panggil sebagai Anda",
  "calling_parked_code": "Dijeda: Kode {{pickupCode}}",
  "calling_call_as_on_behalf_of": "Panggil sebagai {{displayName}}",
  "calling_delegators": "pendelegasi",
  "shortcut_toggle_share_tray": "Alihkan Baki Berbagi.",
  "calling_multiple_participants_hand_raised_mf": "{participantCount, plural, =1{# tangan diangkat} other{# tangan sedang diangkat}}",
  "calling_raise_hand_participants_popup_text_mf": "{participantCount, plural, =1{{name} + # lainnya} other{{name} + # lainnya}}",
  "calling_remote_ptz_camera_indicator_text": "{{name}} mengontrol kamera Anda",
  "calling_splitbutton": "tombolpisah",
  "calling_speedbump_dialog_header": "Anda yakin ingin keluar?",
  "calling_speedbump_dialog_content": "Anda dapat mengecilkan jendela.",
  "calling_speedbump_dialog_checkbox": "Jangan tampilkan lagi",
  "calling_speedbump_dialog_confirm_button": "Tinggalkan",
  "calling_speedbump_dialog_close_button": "Tutup",
  "calling_room_ended_by_timer_description": "Timer ruang terpisah telah kedaluwarsa.",
  "calling_room_ended_by_timer_autojoin_description": "Anda akan bergabung kembali dalam rapat secara otomatis dalam {{autoJoinTimer}}",
  "breakout_rooms_button_disabled_meeting_cancelled": "Ruang terpisah tidak tersedia dalam rapat yang dibatalkan",
  "breakout_rooms_button_disabled_for_non_authorized": "Hanya penyelenggara dan penyaji rapat yang ditentukan yang dapat mengedit",
  "breakout_rooms_button_disabled_too_many_participants": "Ruang terpisah tidak tersedia untuk rapat dengan peserta lebih dari {{limitNumber}} orang",
  "hide_breakoutroom_button": "Sembunyikan ruang terpisah",
  "breakoutroom_count": "Pilih jumlah ruang yang ingin Anda buat.",
  "breakoutroom_settings": "Ruang",
  "breakoutroom_create_rooms_heading": "Membuat ruang terpisah",
  "breakoutroom_participants": "Peserta",
  "breakoutroom_manual_assignment_definition": "Menetapkan orang ke ruang satu per satu.",
  "breakoutroom_room_has_been_selected_mf": "{header, plural, =1{1 ruangan dipilih} other{# ruang dipilih}}",
  "calling_voicemail_mark_as_read": "Tandai Sebagai Dibaca",
  "calling_voicemail_delete": "Hapus",
  "calling_focus_mode": "Fokus",
  "calling_focus_mode_tooltip": "Fokus pada konten bersama",
  "calling_host_view_mode_no_content": "Rapat ini akan segera berlanjut...",
  "callable_channel_failed_to_fetch_call_queue_info_message": "Antrean panggilan Anda saat ini tidak tersedia.",
  "callable_channel_failed_to_change_agent_opt_in_status": "Tidak dapat mengubah status Anda. Coba lagi nanti.",
  "callable_channel_failed_to_fetch_voicemail": "Pesan suara Anda saat ini tidak tersedia.",
  "callable_channel_failed_to_fetch_ra_for_dynamic_caller_id": "Tidak dapat mengakses opsi ID penelepon. Identitas panggilan Anda dibatasi ke akun yang saat ini Anda gunakan.",
  "callable_channel_calls_tab_agents": "Agen",
  "call_queue_agent_status": "{{displayName}} {{presence}} {{optInStatus}}",
  "call_queue_agent_toggle": "Status Keikutsertaan Agen {{displayName}} {{optInStatus}}",
  "call_queue_agents_roster_in_queue_tooltip": "Dalam antrean",
  "call_queue_agents_roster_not_in_queue_tooltip": "Tidak dalam antrean",
  "calling_blocked": "Diblokir",
  "breakoutroom_creating_loader_message": "Kami sedang membuat ruang Anda...",
  "breakoutroom_creating_failure_message": "Kami mengalami masalah saat membuat ruang.",
  "bot_calling_video_not_supported": "Video panggilan bot tidak didukung",
  "bot_calling_audio_not_supported": "Audio panggilan bot tidak didukung",
  "calling_video_preview_header": "Pratinjau pribadi",
  "calling_video_preview_header_with_description": "<0></0> (hanya Anda yang bisa melihat ini)",
  "calling_video_preview_blur_background": "Buramkan latar belakang saya",
  "calling_video_preview_remove_background_effect": "Hapus efek latar belakang",
  "calling_video_preview_background_effects": "Efek latar belakang lainnya",
  "system_audio_driver_install_dialog_header": "Instal driver untuk berbagi suara",
  "system_audio_driver_install_dialog_content": "Ini hanya akan memakan waktu beberapa detik, dan Anda hanya perlu melakukannya sekali.",
  "system_audio_driver_install_dialog_confirm_button": "Instal",
  "system_audio_driver_install_dialog_dismiss_button": "Batal",
  "system_audio_driver_update_dialog_header": "Perbarui driver?",
  "system_audio_driver_update_dialog_content": "Sepertinya driver audio Anda sedikit usang.\nPerbarui ke versi terbaru untuk mendapatkan pengalaman berbagi suara terbaik.",
  "system_audio_driver_update_dialog_confirm_button": "Perbarui",
  "system_audio_driver_update_dialog_dismiss_button": "Jangan sekarang",
  "system_audio_driver_installing_loader_label": "Menginstal",
  "breakout_room_send_announcement_title": "Pengumuman",
  "breakout_room_send_announcement_button_action": "Mengirim",
  "breakout_room_send_announcement_button_cancel_action": "Membatalkan",
  "breakout_room_send_announcement_button_retry_action": "Coba lagi",
  "breakout_room_send_announcement_text": "Membuat pengumuman",
  "breakout_room_send_announcement_successful": "Pengumuman Anda telah dikirim ke semua Ruang Terpisah.",
  "breakout_room_send_announcement_failed": "Tidak dapat mengirim pengumuman Anda.",
  "breakout_room_send_announcement_failed_to_multiple_rooms": "Tidak dapat mengirim pengumuman Anda ke banyak ruang.",
  "breakout_room_send_announcement_failed_one_room": "Tidak dapat mengirim pengumuman Anda ke {{roomName}}.",
  "breakout_room_more_action_button_title": "Opsi lainnya",
  "aria_calling_roster_item_spotlighted": "Disorot",
  "aria_calling_roster_item_content_only": "Audio nonaktif",
  "aria_calling_roster_unmuted": "Suara dinyalakan",
  "aria_has_context_menu": "Memiliki menu konteks",
  "summary_call_aria": "Ringkasan panggilan dengan {{userName}} ditampilkan",
  "summary_voicemail_aria": "Ringkasan pesan suara dengan {{userName}} ditampilkan",
  "resuming": "Melanjutkan",
  "calling_unknown_user": "Pengguna tidak dikenal",
  "calling_meeting_reactions_hand_lowered": "Beri reaksi atau angkat tangan Anda. Tangan Anda tidak diangkat",
  "calling_meeting_reactions_hand_raised": "Beri reaksi atau turunkan tangan Anda. Tangan Anda diangkat",
  "calling_send_meeting_reaction": "{{meetingReactionType}} dikirim",
  "send_like_in_call": "Suka",
  "send_heart_in_call": "Hati",
  "send_laugh_in_call": "Tertawa",
  "calling_parked_row_copied_to_clipboard": "Disalin ke clipboard",
  "send_applause_in_call": "Tepuk Tangan",
  "calling_device_has_been_selected_video_preview": "{{deviceName}} dipilih",
  "breakoutroom_send_announcement_notification": "Pesan pengumuman baru dari penyelenggara",
  "calling_roster_in_meeting_list_title_drill_in": "Dalam rapat ini",
  "calling_roster_return_to_main_panel": "Kembali ke panel Peserta utama",
  "transcript_chat_tile_cancel_button_label": "Batal",
  "transcript_chat_tile_delete_button_label": "Hapus",
  "transcript_chat_tile_delete_dialog_content": "Anda yakin ingin menghapus transkrip ini?",
  "transcript_chat_tile_delete_dialog_header": "Hapus Transkrip",
  "transcript_tmp_anonymous_speaker_name": "Pembicara {{number}}",
  "transcript_tmp_edit_speaker_in_utterance_button_label": "Edit pembicara",
  "transcript_tmp_edit_speaker_no_results_found_label": "Tidak ditemukan hasil",
  "transcript_tmp_edit_speaker_number_of_results_found_label": "{{resultCount}} hasil ditemukan",
  "transcript_tmp_identify_speaker_button_label": "Identifikasi pembicara",
  "transcript_tmp_remove_identification_picker_option_label": "Hapus identifikasi",
  "transcript_tmp_remove_identification_dialog_title": "Hapus semua contoh {{user}}?",
  "transcript_tmp_update_identification_dialog_title": "Perbarui semua contoh {{user}} ke {{newUser}}?",
  "transcript_failed_edit_dialog_title": "Tidak dapat mengedit pembicara",
  "transcript_tmp_remove_identification_multiple_utterances_button_label": "Hapus semua",
  "transcript_tmp_update_identification_multiple_utterances_button_label": "Perbarui semua",
  "transcript_tmp_update_identification_single_utternace_button_label": "Hanya yang ini",
  "transcript_tmp_update_identification_dialog_close": "Tutup",
  "transcript_tmp_utterance_device_source_name_label": "{{user}}",
  "transcript_tmp_edit_speaker_edited_aria_label": "Diedit oleh {{user}} dan {{ariaLabelHasContextMenu}}",
  "transcript_tmp_edit_speaker_edited_utterance_label": "Diedit oleh {{user}}",
  "transcript_tmp_edit_speaker_edited_tag": "Diedit",
  "transcript_tmp_banner_close_button": "Tutup",
  "transcript_tmp_recognition_enrollment_header": "Siapkan pengenal suara Teams untuk membantu kami mengidentifikasi Anda di Rapat mendatang.",
  "transcript_tmp_recognition_enrollment_button_text": "Mulai",
  "transcript_tmp_recognition_enrollment_aria_label": "Mulai pengenalan suara",
  "transcript_tmp_attribution_issues_banner_header": "Kami tidak dapat mengidentifikasi setiap pembicara di ruang.",
  "transcript_tmp_attribution_issues_banner_link_text": "Pelajari selengkapnya",
  "transcript_tmp_attribution_issues_banner_aria_label": "Pelajari alasan kami tidak dapat mengidentifikasi semua pembicara di ruang",
  "aria_calling_roster_unable_to_unmute": "Tidak dapat menyalakan suara",
  "calling_roster_in_meeting_list_title_search": "Dalam rapat ini",
  "calling_roster_not_in_meeting_list_title_search": "Tidak dalam rapat ini",
  "calling_roster_in_lobby_list_title_search": "Di lobi",
  "roster_participants_search_no_match_render_title": "Kami tidak menemukan kecocokan.",
  "roster_participants_search_match_found_render": "Kami menemukan kecocokan untuk riset {{name}}.",
  "roster_participants_search_failed_render_title": "Pencarian gagal.",
  "roster_participants_search_failed_retry": "Coba lagi",
  "calling_roster_button_add_phone": "Tambahkan telepon",
  "roster_participants_search_placeholder": "Temukan peserta",
  "aria_raise_hand_multiple_participants_mf": "{participantCount, plural, =1{{name} + # lainnya mengangkat tangan} other{{name} + # lainnya mengangkat tangan}}",
  "aria_raise_hand_multiple_participants_without_name": "{{participantCount}} orang mengangkat tangan",
  "calling_stop_presenting_confirm": "Berhenti menyajikan",
  "calling_stop_presenting_header": "Berhenti menyajikan?",
  "calling_stop_presenting_text": "Ini akan mengakhiri presentasi untuk semua orang. Untuk beralih penyaji, pilih Batal sehingga orang berikutnya dapat mengambil kendali",
  "calling_stop_presenting_close_button": "Tutup",
  "calling_confirm_mute_all_presenters_dialog_title": "Matikan suara semua penyaji?",
  "calling_confirm_mute_all_presenters_dialog_text": "Ini akan mematikan suara semua penyaji dalam rapat, kecuali Anda.",
  "calling_confirm_mute_all_attendees_dialog_title": "Matikan suara semua peserta?",
  "calling_confirm_mute_all_attendees_dialog_text": "Mereka masih bisa mematikan suara sendiri.",
  "calling_ppt_loading_message_preparing_slides": "Mempersiapkan slide Anda...",
  "calling_ppt_loading_message_loading_presentation": "Memuat presentasi Anda...",
  "calling_ppt_loading_message_working_out_details": "Sedang memproses beberapa detail...",
  "calling_ppt_loading_message_slides_will_appear": "Slide akan muncul di sini saat sudah siap...",
  "calling_ppt_loading_message_still_working": "Masih mengerjakannya...",
  "calling_ppt_loading_message_reload": "Hmm… kami mengalami kesulitan memuat presentasi Anda. Anda dapat menunggu sebentar lagi atau mencoba memuat ulang.",
  "calling_ppt_reload_error_screen_button": "Muat ulang",
  "calling_ppt_reload_error_screen_title": "Muat ulang untuk menampilkan presentasi",
  "calling_ppt_reload_error_screen_message": "Terjadi kesalahan saat memuat presentasi. Coba muat ulang.",
  "calling_ppt_reload_error_screen_report_an_issue": "Laporkan masalah.",
  "calling_roster_invite_from_chat_title": "Orang lain dari obrolan",
  "calling_content_camera_picker_bar_title": "Konten dari kamera",
  "calling_whiteboard_camera_title": "Papan Tulis",
  "calling_aria_audio_participants": "Peserta dengan kamera nonaktif",
  "calling_aria_video_participants": "Peserta dengan kamera aktif",
  "calling_aria_pinned_participants": "Peserta yang disematkan dan disorot",
  "calling_aria_has_context_menu": "Menu konteks tersedia",
  "calling_is_me_video": "Video saya sendiri, memiliki menu konteks",
  "calling_is_me_video_spotlighted": "Video saya sendiri, disorot, memiliki menu konteks",
  "aria_meeting_info_back_button_click": "Kembali",
  "aria_meeting_info_button_click": "Informasi rapat",
  "meeting_fluid_open_in_onenote": "Buka di OneNote",
  "meeting_info": "Info rapat virtual",
  "meeting_locked_screen_title": "Rapat ini dikunci",
  "meeting_locked_screen_text": "Tidak ada orang lain yang dapat bergabung.",
  "meeting_lock_button_title": "Kunci rapat",
  "meeting_unlock_button_title": "Buka kunci rapat",
  "meeting_lock_dialog_title": "Kunci rapat?",
  "meeting_lock_dialog_text": "Tidak ada orang lain yang dapat bergabung, tetapi undangan masih dapat mengakses obrolan rapat, rekaman, dan Info rapat lainnya.",
  "meeting_lock_dialog_button_title": "Kunci",
  "meeting_details_add_fluid_button": "Tambahkan",
  "meeting_details_add_fluid_instruction_topic": "Tambahkan agenda dan catatan",
  "meeting_details_add_fluid_instruction": "Sertakan agenda, catatan, dan tugas yang dapat diedit oleh setiap orang yang diundang.",
  "meeting_details_refresh_button": "Refresh untuk mendapatkan catatan bersama",
  "meeting_details_title": "Detail",
  "meeting_unlock_dialog_title": "Buka kunci rapat",
  "meeting_unlock_dialog_text": "Orang akan dapat bergabung.",
  "meeting_unlock_dialog_button_title": "Buka kunci",
  "meeting_lock_retry_dialog_title": "Tidak dapat mengunci rapat",
  "meeting_lock_retry_dialog_text": "Terjadi kesalahan. Coba kunci lagi.",
  "meeting_lock_retry_dialog_button_title": "Coba lagi",
  "meeting_unlock_retry_dialog_title": "Tidak dapat membuka kunci rapat",
  "meeting_unlock_retry_dialog_text": "Terjadi kesalahan. Coba buka kunci lagi.",
  "calendar_private_meeting_title": "Rapat Pribadi",
  "calendar_no_upcoming_meetings_text": "Ruang tersebut tersedia hingga hari ini berakhir",
  "join_by_code_button_content": "Bergabung menggunakan Kode",
  "meeting_unlock_for_breakoutrooms_dialog_title": "Buka kunci rapat untuk membuat ruang terpisah",
  "meeting_unlock_for_breakoutrooms_dialog_text": "Ruang terpisah tidak tersedia saat rapat terkunci.",
  "aria_label_meeting_view": "Tampilan rapat",
  "aria_label_more_participants_on_stage": "{{hiddenItemsCount}} peserta lainnya",
  "start_annotation_button_title": "Mulai anotasi",
  "meeting_time_interval": "{{startTime}} - {{endTime}}",
  "stop_annotation_button_title": "Hentikan anotasi",
  "calling_recording_and_transcript_label": "Perekaman dan transkripsi",
  "rtflyout_calling_recording_and_transcript_label": "Perekaman dan transkripsi",
  "calling_content_camera_sharing_scan_again_title": "Pindai lagi",
  "calling_content_camera_sharing_enhancement_title": "Peningkatan",
  "calling_content_camera_enhancement_advanced_title": "Lanjutan",
  "calling_content_camera_enhancement_basic_title": "Dasar",
  "calling_content_camera_enhancement_none_title": "Tidak ada",
  "calling_enable_narrow_mode": "Galeri di paling atas",
  "calling_screensharing_request_control_dialog_cancel_button": "Batal",
  "calling_screensharing_request_control_dialog_confirm_button": "Permintaan",
  "calling_screensharing_release_control_confirmation": "Kontrol layar telah dihentikan",
  "calling_screensharing_request_control_dialog_title": "Meminta kontrol?",
  "calling_screensharing_request_control_dialog_text": "Anda akan mengontrol konten yang dibagikan penyaji.",
  "calling_screensharing_control_given": "Anda telah diberi kontrol layar",
  "calling_content_camera_setup_dialog_share_button_title": "Berbagi",
  "calling_content_camera_setup_dialog_scan_again_button_title": "Pindai Lagi",
  "sharetray_previews": "Pratinjau untuk baki berbagi",
  "aria_label_raise_hand_self": "Anda",
  "aria_label_no_raise_hands": "Tidak ada yang mengangkat tangan",
  "aria_label_hands_raised_list_mf": "{raiseHandCount, plural, =1{# mengangkat tangan. {names}} other{# mengangkat tangan (daftar tidak diurutkan). {names}}}",
  "calling_raisehand_win": "Naikkan tangan (Ctrl+Shift+K)",
  "calling_raisehand_mac": "Naikkan tangan (⌘+Shift+K)",
  "calling_lowerhand_win": "Turunkan tangan (Ctrl+Shift+K)",
  "calling_lowerhand_mac": "Turunkan tangan (⌘+Shift+K)",
  "calling_pstn_LBR_error": "Panggilan tidak diperbolehkan karena pengaturan organisasi Anda",
  "calling_pstn_number_type_phone": "Telepon",
  "calling_pstn_number_type_mobile": "Ponsel",
  "calling_pstn_number_type_other": "Lainnya",
  "calling_document_camera_title": "Dokumen",
  "calling_document_camera_setup_dialog_camera_consent_title": "Anda perlu mengaktifkan kamera untuk memindai dokumen.",
  "calling_document_content_type_setup_dialog_dropdown_item": "Dokumen",
  "calling_whiteboard_content_type_setup_dialog_dropdown_item": "Papan Tulis",
  "calling_video_content_type_setup_dialog_dropdown_item": "Video",
  "calling_content_sharing_preview_screen_content_type_dropdown_title": "Tipe konten",
  "calling_content_type_has_been_selected_content_scan_preview": "{{contentType}} dipilih",
  "calling_content_camera_sharing_sub_title": "Bagikan dokumen, papan tulis, dan banyak lagi",
  "calling_noise_suppression_title": "Peredam kebisingan",
  "calling_noise_suppression_tooltip": "Redam suara latar belakang yang bukan ucapan",
  "calling_noise_aria_suppression_switch": "Aktifkan peredam kebisingan",
  "calling_noise_suppression_mode_auto": "Otomatis (default)",
  "calling_noise_suppression_mode_high": "Tinggi",
  "calling_noise_suppression_mode_low": "Rendah",
  "calling_noise_suppression_mode_off": "Tidak Aktif",
  "calling_noise_suppression_description": "Pilih Rendah jika Anda ingin orang lain mendengar musik.",
  "calling_noise_suppression_learn_more": "Pelajari selengkapnya",
  "calling_noise_suppression_aria_learn_more": "Peredam Kebisingan. Meredam suara latar belakang yang bukan ucapan. Pelajari Selengkapnya.",
  "calling_noise_suppression_aria_selected": "{{ header }} dipilih.",
  "calling_user_left": "Anda telah meninggalkan grup panggilan",
  "broadcast_restart_event_button": "Mulai Ulang Acara",
  "calling_content_camera_toolbar_rotate_tooltip": "Putar",
  "calling_content_camera_toolbar_snapshot_tooltip": "Snapshot",
  "calling_content_camera_toolbar_settings_tooltip": "Pengaturan",
  "calling_content_camera_toolbar_cleanup_on_tooltip": "Jangan overlay penyaji",
  "calling_content_camera_toolbar_cleanup_off_tooltip": "Overlay penyaji",
  "calling_content_camera_toolbar_quad_detection_on_tooltip": "Jangan deteksi tepi",
  "calling_content_camera_toolbar_quad_detection_off_tooltip": "Deteksi tepi",
  "calling_content_camera_snapshot_image_alt_text": "Gambar Rekam Jepret",
  "calling_pagination_page_number": "{{currentPage}}/{{pageCount}}",
  "calling_pagination_aria_live_announcement": "Halaman {{currentPage}}/{{pageCount}} dipilih",
  "calling_pagination_next_page": "Halaman berikutnya",
  "calling_pagination_next_page_narration": "Navigasikan ke halaman video berikutnya. Saat ini {{currentPage}}/{{pageCount}}",
  "calling_pagination_prev_page": "Halaman sebelumnya",
  "calling_pagination_prev_page_narration": "Navigasikan ke halaman video sebelumnya. Saat ini {{currentPage}}/{{pageCount}}",
  "calling_ubar_meeting_apps_add": "Tambahkan aplikasi",
  "work_location": "Lokasi kerja",
  "location_not_editable": "Lokasi tidak dapat diedit",
  "add_address": "Tambahkan alamat Anda",
  "edit_address": "Edit alamat Anda",
  "confirm_address": "Konfirmasikan alamat Anda",
  "current_emergency_location": "Lokasi darurat Anda saat ini",
  "location_not_detected": "Lokasi tidak terdeteksi",
  "emergency_location_settings_text": "Pengaturan lokasi darurat",
  "edit_your_current_location": "Edit lokasi Anda saat ini",
  "confirm_your_current_location": "Konfirmasikan lokasi Anda saat ini",
  "all_fields_required": "(Semua bidang wajib diisi.)",
  "confirm_emergency_address": "Konfirmasikan",
  "add_new_address": "Tambahkan alamat baru",
  "add_your_address": "Tambahkan alamat Anda",
  "add_emergency_address": "Tambahkan",
  "search_for_address": "Cari alamat",
  "searching_for_address": "Sedang mencari...",
  "no_match_for_address": "Tidak ditemukan kecocokan.",
  "address_number": "Nomor",
  "address_street": "Jalan",
  "address_city": "Kota",
  "address_state": "Provinsi",
  "address_zipcode": "Kode pos",
  "calling_retry_screen_invalid_meeting_code": "Kami tidak dapat menemukan rapat yang terkait dengan ID ini.",
  "aria_meeting_code_input_label": "ID Rapat",
  "aria_calling_roster_unable_to_video_unmute": "Tidak dapat berbagi video",
  "calling_whiteboard_camera_subtitle": "Gunakan kamera perangkat untuk berbagi papan tulis di sekitar.",
  "calling_document_camera_subtitle": "Gunakan kamera eksternal untuk berbagi dokumen.",
  "calling_meeting_room_content_only": "Hanya Konten",
  "calling_meeting_room_content_only_aria": "HanyaKonten",
  "calling_meeting_room_content_only_badgeText_default": "Hanya Konten",
  "calling_meeting_room_content_and_people": "Konten + Orang",
  "calling_meeting_room_content_and_people_aria": "Konten + Orang",
  "calling_meeting_room_content_and_people_badgeText_default": "Konten + Orang",
  "calling_meeting_room_people_only": "Hanya Orang",
  "calling_meeting_room_people_only_aria": "Hanya Orang",
  "calling_meeting_room_people_only_badgeText_default": "Hanya Orang",
  "calling_video_camera_title": "Video",
  "calling_video_camera_subtitle": "Bagikan video langsung secara real time.",
  "calling_roster_header_hard_mute_button_v2": "Nonaktifkan mikrofon untuk peserta",
  "calling_roster_header_hard_mute_dialog_confirm_v2": "Nonaktifkan mikrofon",
  "calling_roster_header_hard_mute_dialog_content_v2": "Peserta tidak akan dapat menyalakan suara sendiri. Penyelenggara dan penyaji dapat mengizinkan orang menyalakan suara jika diperlukan.",
  "calling_roster_header_hard_mute_dialog_title_v2": "Nonaktifkan mikrofon untuk peserta?",
  "calling_roster_header_hard_unmute_button_v2": "Izinkan mikrofon untuk peserta",
  "calling_roster_header_hard_unmute_dialog_confirm_v2": "Izinkan mikrofon",
  "calling_roster_header_hard_unmute_dialog_content_v2": "Semua peserta rapat akan dapat menyalakan suara sendiri.",
  "calling_roster_header_hard_unmute_dialog_title_v2": "Izinkan mikrofon untuk peserta?",
  "calling_restrict_attendees_video_option_text_v2": "Nonaktifkan kamera untuk peserta",
  "calling_restrict_attendees_video_confirm_dialog_confirm_v2": "Nonaktifkan kamera",
  "calling_restrict_attendees_video_confirm_dialog_content_v2": "Peserta tidak akan dapat membagikan video. Penyelenggara dan penyaji dapat mengizinkan orang mengaktifkan kameranya jika diperlukan.",
  "calling_restrict_attendees_video_confirm_dialog_title_v2": "Nonaktifkan kamera untuk peserta?",
  "calling_unrestrict_attendees_video_option_text_v2": "Izinkan kamera untuk peserta",
  "calling_unrestrict_attendees_video_confirm_dialog_confirm_v2": "Izinkan kamera",
  "calling_unrestrict_attendees_video_confirm_dialog_content_v2": "Semua orang dalam rapat akan dapat membagikan video.",
  "calling_unrestrict_attendees_video_confirm_dialog_title_v2": "Izinkan kamera untuk peserta?",
  "calling_request_to_speak_allow_unmute_v2": "Izinkan mikrofon",
  "calling_request_to_speak_disallow_unmute_v2": "Nonaktifkan mikrofon",
  "calling_restrict_attendee_video_option_text_v2": "Nonaktifkan kamera",
  "calling_unrestrict_attendee_video_option_text_v2": "Izinkan kamera",
  "aria_calling_video_hard_mute_attendees_able_to_unmute": "Peserta kini dapat membagikan video",
  "aria_calling_video_hard_mute_attendees_unable_to_unmute": "Peserta tidak dapat membagikan video",
  "aria_calling_video_hard_mute_attendee_able_to_unmute": "{{participantName}} kini dapat berbagi video",
  "aria_calling_video_hard_mute_attendee_unable_to_unmute": "{{participantName}} tidak dapat berbagi video",
  "calling_video_restricted_tooltip_mw": "Hanya pilih peserta yang dapat berbagi video",
  "calling_microphone_disabled_by_hard_mute_v2": "Hanya pilih peserta yang dapat menyalakan suara",
  "calling_video_disabled_during_content_camera_sharing": "Anda sedang membagikan konten dari kamera",
  "calling_breakout_rooms_take_control_from_participant": "{{participant}} sedang mengelola ruang",
  "calling_breakout_rooms_take_control_from_no_one": "Tidak ada yang mengelola ruang",
  "calling_breakout_rooms_take_control_from_myself": "Anda mengontrol dari perangkat lain",
  "calling_breakout_rooms_take_control_error": "Terjadi kesalahan. Coba lagi",
  "calling_breakout_rooms_take_control_button": "Kelola ruang",
  "calling_breakout_rooms_take_control_from_myself_button": "Kelola ruang di sini",
  "calling_breakout_rooms_take_control_confirmation_title": "Mengambil kendali",
  "calling_breakout_rooms_take_control_confirmation_content": "Jika Anda mengambil kontrol, manajer saat ini akan kehilangan semua tindakan yang belum selesai.",
  "calling_breakout_rooms_take_control_confirmation_button": "Konfirmasikan",
  "calling_turning_off_camera": "Mengaktifkan kamera...",
  "calling_confirm_mute_all_attendees_unrestricted_dialog_text": "Peserta yang mikrofonnya diaktifkan masih akan dapat menyalakan suara sendiri.",
  "lower_all_raised_hands": "Turunkan semua tangan",
  "confirm_lower_all_raised_hands_dialog_title": "Turunkan semua tangan?",
  "aria_calling_confirm_lower_all_raised_hands_dialog_text_mf": "{number, plural, =1{Anda akan menurunkan {number} tangan terangkat.} other{Anda akan menurunkan {number} tangan terangkat.}}",
  "aria_calling_breakout_rooms_room_status_closed_mf": "{number, plural, =1{{roomName} ditutup. # peserta.} other{{roomName} ditutup. # peserta.}}",
  "aria_calling_breakout_rooms_room_status_open_mf": "{number, plural, =1{{roomName} terbuka. # peserta.} other{{roomName} terbuka. # peserta.}}",
  "breakout_rooms_demote_manager_to_attendee_dialog_title": "Anda didemosikan menjadi peserta",
  "breakout_rooms_demote_manager_as_presenter_dialog_title": "Anda dihapus dari daftar manajer",
  "breakout_rooms_demote_manager_as_presenter_dialog_content": "Penyelenggara telah menarik kemampuan mengelola ruang terpisah",
  "breakout_rooms_demote_manager_dialog_acknowledge_button": "Oke",
  "ufd_close_dialog": "Tutup dialog",
  "live_streaming_confirmation_dialog_header": "Konfirmasikan streaming konten rapat?",
  "live_streaming_confirmation_dialog_content": "Teams perlu mengakses dan membagikan konten rapat Anda ke platform atau layanan eksternal selama rapat ini.",
  "live_streaming_confirmation_dialog_allow_button_text": "Izinkan",
  "live_streaming_confirmation_dialog_cancel_button_text": "Batal",
  "calling_feedback_button_report": "Laporkan masalah",
  "calling_content_camera_learn_more": "Pelajari selengkapnya",
  "calling_content_camera_detecting_edges": "Mendeteksi tepi",
  "calling_content_camera_edge_detection_successfull": "Tepi terdeteksi",
  "calling_content_camera_edge_detection_turn_off": "Deteksi tepi dinonaktifkan",
  "calling_content_camera_clean_up_turn_on": "Penyaji overlay diaktifkan",
  "calling_content_camera_clean_up_turn_off": "Penyaji overlay dinonaktifkan",
  "calling_content_camera_snapshot_taken": "Rekam jepret dilampirkan dalam obrolan"
}